bootstrap4_nav/__init__.py
bootstrap4_nav/__meta__.py
bootstrap4_nav/context_processors.py
bootstrap4_nav/models.py
bootstrap4_nav/settings.py
bootstrap4_nav/utils.py
bootstrap4_nav/__pycache__/__init__.cpython-36.pyc
bootstrap4_nav/__pycache__/__init__.cpython-38.pyc
bootstrap4_nav/__pycache__/__meta__.cpython-36.pyc
bootstrap4_nav/__pycache__/__meta__.cpython-38.pyc
bootstrap4_nav/__pycache__/context_processors.cpython-36.pyc
bootstrap4_nav/__pycache__/context_processors.cpython-38.pyc
bootstrap4_nav/__pycache__/models.cpython-36.pyc
bootstrap4_nav/__pycache__/models.cpython-38.pyc
bootstrap4_nav/__pycache__/settings.cpython-36.pyc
bootstrap4_nav/__pycache__/settings.cpython-38.pyc
bootstrap4_nav/__pycache__/utils.cpython-36.pyc
bootstrap4_nav/__pycache__/utils.cpython-38.pyc
bootstrap4_nav/migrations/__init__.py
bootstrap4_nav/migrations/__pycache__/__init__.cpython-36.pyc
bootstrap4_nav/migrations/__pycache__/__init__.cpython-38.pyc
bootstrap4_nav/static/bootstrap4_nav/bootstrap4_nav.css
bootstrap4_nav/static/bootstrap4_nav/bootstrap4_nav.js
bootstrap4_nav/templates/bootstrap4_nav/400.html
bootstrap4_nav/templates/bootstrap4_nav/403.html
bootstrap4_nav/templates/bootstrap4_nav/404.html
bootstrap4_nav/templates/bootstrap4_nav/500.html
bootstrap4_nav/templates/bootstrap4_nav/base.html
bootstrap4_nav/templates/bootstrap4_nav/begin_body.html
bootstrap4_nav/templates/bootstrap4_nav/end_body.html
bootstrap4_nav/templates/bootstrap4_nav/footer.html
bootstrap4_nav/templates/bootstrap4_nav/head.html
bootstrap4_nav/templates/bootstrap4_nav/messages.html
bootstrap4_nav/templates/bootstrap4_nav/navbar.html
bootstrap4_nav/templates/bootstrap4_nav/navbar_items.html
bootstrap4_nav/templates/bootstrap4_nav/sidenav.html
bootstrap4_nav/templates/bootstrap4_nav/sidenav_items.html
bootstrap4_nav/templates/registration/logged_out.html
bootstrap4_nav/templates/registration/login.html
bootstrap4_nav/templates/registration/password_change_done.html
bootstrap4_nav-1.0.0.dist-info/LICENSE
bootstrap4_nav-1.0.0.dist-info/METADATA
bootstrap4_nav-1.0.0.dist-info/WHEEL
bootstrap4_nav-1.0.0.dist-info/top_level.txt
bootstrap4_nav-1.0.0.dist-info/RECORD
